Metadata-Version: 2.1
Name: MutPy
Version: 0.6.1
Summary: Mutation testing tool for Python 3.x source code.
Home-page: https://github.com/mutpy/mutpy
Author: Konrad Hałas
Author-email: halas.konrad@gmail.com
License: UNKNOWN
Download-URL: https://github.com/mutpy/mutpy
Platform: UNKNOWN
Classifier: Programming Language :: Python :: 3.4
Classifier: Programming Language :: Python :: 3.5
Classifier: Programming Language :: Python :: 3.6
Classifier: Programming Language :: Python :: 3.7
Classifier: Environment :: Console
Classifier: Intended Audience :: Developers
Classifier: Topic :: Software Development :: Testing
Classifier: License :: OSI Approved :: Apache Software License
Requires-Python: >=3.3
Provides-Extra: pytest
